pca_trame-0.0.11.dist-info/licenses/LICENCE
trame/__init__.py
trame/config.py
trame/hasher.py
trame/piece/__init__.py
trame/piece/consolidate.py
trame_tests/__init__.py
trame_tests/__main__.py
trame_tests/get_trame.py
trame_tests/test_0_piece_builder.py
trame_tests/test_10_md_content_hash.py
trame_tests/test_1_piece_model.py
trame_tests/test_2_trame_builder.py
trame_tests/test_3_trame_builder_smoketest.py
trame_tests/test_4_yaml_parsing.py
trame_tests/test_5_metadata.py
trame_tests/test_6_images.py
trame_tests/test_7_footnotes.py
trame_tests/test_8_blockquotes.py
trame_tests/test_9_hasher.py
trame_tests/data/330px-Johannes_Gutenberg.jpg
trame_tests/data/dummy.md
trame_tests/data/nav_et_trigo.md
trame_tests/data/obvious-style.css
trame_tests/data/rgpd.md
trame_tests/data/rgpd_maths.pm.md
trame_tests/data/sujet_0_spe_sujet_1.md
trame_tests/data/sujet_0_spe_sujet_2.md
trame_tests/sandbox/__init__.py
trame_tests/sandbox/__main__.py
pca_trame-0.0.11.dist-info/METADATA
pca_trame-0.0.11.dist-info/WHEEL
pca_trame-0.0.11.dist-info/top_level.txt
pca_trame-0.0.11.dist-info/RECORD
