Metadata-Version: 2.4
Name: pca-trame
Version: 0.0.11
Author: Etienne Madinier
Maintainer: Etienne Madinier
Requires-Python: >=3.13
License-File: LICENCE
Requires-Dist: pydantic==2.12.5
Requires-Dist: markdown==3.10
Requires-Dist: bs4==0.0.2
Requires-Dist: strictyaml==1.7.3
Provides-Extra: dev
Requires-Dist: build==1.3.0; extra == "dev"
Requires-Dist: djlint==1.36.4; extra == "dev"
Requires-Dist: black==24.4.2; extra == "dev"
Requires-Dist: ruff==0.11.2; extra == "dev"
Requires-Dist: jinja2==3.1.6; extra == "dev"
Requires-Dist: twine==6.2.0; extra == "dev"
Dynamic: license-file
